cgn_pytorch/__init__.py
cgn_pytorch/checkpoints/config.yaml
cgn_pytorch/checkpoints/current.pth
cgn_pytorch/contact_graspnet.py
cgn_pytorch/dataset.py
cgn_pytorch/gripper/control_points/panda.npy
cgn_pytorch/gripper/control_points/panda_gripper_big.yaml
cgn_pytorch/gripper/control_points/panda_gripper_coords.pickle
cgn_pytorch/gripper/control_points/panda_gripper_coords.yaml
cgn_pytorch/gripper/mesh/panda_gripper/finger.stl
cgn_pytorch/gripper/mesh/panda_gripper/hand.stl
cgn_pytorch/gripper/mesh/panda_gripper/panda_gripper.obj
cgn_pytorch/gripper/mesh/robotiq_arg2f_140_outer_finger.stl
cgn_pytorch/gripper/mesh/robotiq_arg2f_base_link.stl
cgn_pytorch/inference.py
cgn_pytorch/pointnet2.py
cgn_pytorch/scenes/002330.npz
cgn_pytorch/scenes/004086.npz
cgn_pytorch/scenes/005274.npz
cgn_pytorch/util/__init__.py
cgn_pytorch/util/config_utils.py
cgn_pytorch/util/data_utils.py
cgn_pytorch/util/mesh_utils.py
cgn_pytorch/util/pcd_utils.py
cgn_pytorch/util/pointnet2/__init__.py
cgn_pytorch/util/pointnet2/models.py
cgn_pytorch/util/scene_renderer.py
cgn_pytorch/util/test_meshcat_pcd.py
cgn_pytorch-0.4.3.dist-info/METADATA
cgn_pytorch-0.4.3.dist-info/WHEEL
cgn_pytorch-0.4.3.dist-info/RECORD
