Metadata-Version: 2.1
Name: cgn-pytorch
Version: 0.4.3
Summary: Pytorch implementation of Contact Graspnet
License: MIT
Keywords: artificial intelligence,deep learning,grasping,robotics,contact grasp net
Author: Sebastian Peralta
Author-email: peraltas@seas.upenn.edu
Requires-Python: >=3.9,<4.0
Classifier: Development Status :: 4 - Beta
Classifier: Intended Audience :: Developers
Classifier: License :: OSI Approved :: MIT License
Classifier: Programming Language :: Python :: 3
Classifier: Programming Language :: Python :: 3.9
Classifier: Programming Language :: Python :: 3.10
Classifier: Programming Language :: Python :: 3.11
Classifier: Programming Language :: Python :: 3.12
Classifier: Topic :: Scientific/Engineering :: Artificial Intelligence
Requires-Dist: asttokens (==2.4.1)
Requires-Dist: certifi (==2023.11.17)
Requires-Dist: charset-normalizer (==3.3.2)
Requires-Dist: decorator (==5.1.1)
Requires-Dist: exceptiongroup (==1.2.0)
Requires-Dist: executing (==2.0.1)
Requires-Dist: filelock (==3.13.1)
Requires-Dist: fsspec (==2023.10.0)
Requires-Dist: idna (==3.4)
Requires-Dist: importlib-resources (==6.1.1)
Requires-Dist: ipython (==8.17.2)
Requires-Dist: jedi (==0.19.1)
Requires-Dist: jinja2 (==3.1.2)
Requires-Dist: joblib (==1.3.2)
Requires-Dist: markupsafe (==2.1.3)
Requires-Dist: matplotlib-inline (==0.1.6)
Requires-Dist: meshcat (==0.3.2)
Requires-Dist: mpmath (==1.3.0)
Requires-Dist: networkx (==3.2.1)
Requires-Dist: numpy (==1.26.2)
Requires-Dist: parso (==0.8.3)
Requires-Dist: pexpect (==4.8.0)
Requires-Dist: pillow (==10.1.0)
Requires-Dist: prompt-toolkit (==3.0.41)
Requires-Dist: psutil (==5.9.6)
Requires-Dist: ptyprocess (==0.7.0)
Requires-Dist: pure-eval (==0.2.2)
Requires-Dist: pygments (==2.17.2)
Requires-Dist: pyngrok (==7.0.1)
Requires-Dist: pyparsing (==3.1.1)
Requires-Dist: pyrender (>=0.1.45,<0.2.0)
Requires-Dist: pyyaml (==6.0.1)
Requires-Dist: pyzmq (==25.1.1)
Requires-Dist: requests (==2.31.0)
Requires-Dist: scikit-learn (==1.3.2)
Requires-Dist: scipy (==1.11.4)
Requires-Dist: six (==1.16.0)
Requires-Dist: stack-data (==0.6.3)
Requires-Dist: sympy (==1.12)
Requires-Dist: threadpoolctl (==3.2.0)
Requires-Dist: torch (==2.1.1)
Requires-Dist: torch-cluster (>=1.6.3,<2.0.0)
Requires-Dist: torch-geometric (==2.4.0)
Requires-Dist: tornado (==6.3.3)
Requires-Dist: tqdm (==4.66.1)
Requires-Dist: traitlets (==5.13.0)
Requires-Dist: trimesh (==4.0.4)
Requires-Dist: typeguard (==4.1.5)
Requires-Dist: typing-extensions (==4.8.0)
Requires-Dist: u-msgpack-python (==2.8.0)
Requires-Dist: urllib3 (==2.1.0)
Requires-Dist: wcwidth (==0.2.12)
